ratp_api/__init__.py
ratp_api/main.py
ratp_api/affluence/__init__.py
ratp_api/affluence/line_mappings.py
ratp_api/models/__init__.py
ratp_api/models/line.py
ratp_api-1.0.3.dist-info/METADATA
ratp_api-1.0.3.dist-info/WHEEL
ratp_api-1.0.3.dist-info/top_level.txt
ratp_api-1.0.3.dist-info/RECORD
