Metadata-Version: 2.1
Name: ratp_api
Version: 1.0.3
Summary: Get RATP data from RATP API.
Home-page: https://github.com/tomchen/example_pypi_package
Author: Roméo Phillips
Author-email: phillipsromeo@gmail.com
Project-URL: Documentation, https://github.com/Strvm/ratp-api-python
Project-URL: Bug Reports, https://github.com/Strvm/ratp-api-python
Project-URL: Source Code, https://github.com/Strvm/ratp-api-python
Keywords: ratp,rer,metro,api,ratp_api,ratp_api-python
Classifier: Development Status :: 5 - Production/Stable
Classifier: Intended Audience :: Developers
Classifier: Topic :: Software Development :: Build Tools
Classifier: Programming Language :: Python :: 3
Classifier: Programming Language :: Python :: 3.6
Classifier: Programming Language :: Python :: 3.7
Classifier: Programming Language :: Python :: 3.8
Classifier: Programming Language :: Python :: 3.9
Classifier: Programming Language :: Python :: 3 :: Only
Classifier: License :: OSI Approved :: MIT License
Classifier: Operating System :: OS Independent
Requires-Python: >=3.6
Requires-Dist: requests
Requires-Dist: pydantic
Provides-Extra: dev
Requires-Dist: check-manifest ; extra == 'dev'
